compose_operator.py
compose_operator-1.0.3.dist-info/LICENSE
compose_operator-1.0.3.dist-info/METADATA
compose_operator-1.0.3.dist-info/WHEEL
compose_operator-1.0.3.dist-info/top_level.txt
compose_operator-1.0.3.dist-info/RECORD
