Metadata-Version: 2.1
Name: compose-operator
Version: 1.0.3
Summary: Operator overload for function composition.
Home-page: https://github.com/mentalisttraceur/python-compose-operator
Author: Alexander Kozhevnikov
Author-email: mentalisttraceur@gmail.com
License: 0BSD
Classifier: Development Status :: 5 - Production/Stable
Classifier: Programming Language :: Python :: 3
Classifier: Operating System :: OS Independent
Requires: compose (>=1.4.8)
Requires: wrapt (>=1.15.0)
Requires-Python: >=3.8
License-File: LICENSE
